QACTPBeeBroker/__init__.py
QACTPBeeBroker/setting.py
QACTPBeeBroker/sub.py
QACTPBeeBroker-1.5.dist-info/METADATA
QACTPBeeBroker-1.5.dist-info/RECORD
QACTPBeeBroker-1.5.dist-info/WHEEL
QACTPBeeBroker-1.5.dist-info/entry_points.txt
QACTPBeeBroker-1.5.dist-info/top_level.txt
QACTPBeeBroker-1.5.dist-info/zip-safe
