Metadata-Version: 2.1
Name: QACTPBeeBroker
Version: 1.5
Summary: QACTPBeeBroker: broker for ctp bee
Home-page: https://github.com/yutiansut/QACTPBEEBROKER
Author: yutiansut
Author-email: yutiansut@qq.com
License: MIT
Keywords: quantaxis,quant,finance,Backtest,Framework
Platform: UNKNOWN
Classifier: License :: OSI Approved :: MIT License
Classifier: Programming Language :: Python
Classifier: Intended Audience :: Developers
Classifier: Operating System :: OS Independent
Requires-Dist: quantaxis
Requires-Dist: quantaxis-pubsub (>=1.6.3)
Requires-Dist: ctpbee
